{"sentences": [{"tokens": [{"text": "Judecătorii", "id": "w2"}, {"text": "EULEX", "id": "w3"}, {"text": "condamnă", "id": "w4"}, {"text": "un", "id": "w5"}, {"text": "fost", "id": "w6"}, {"text": "luptător", "id": "w7"}, {"text": "KLA", "id": "w8"}, {"text": "pentru", "id": "w9"}, {"text": "crime", "id": "w10"}, {"text": "comise", "id": "w11"}, {"text": "în", "id": "w12"}, {"text": "1998", "id": "w13"}], "id": "w1"}, {"tokens": [{"text": "05", "id": "w15"}, {"text": "/", "id": "w16"}, {"text": "03", "id": "w17"}, {"text": "/", "id": "w18"}, {"text": "2009", "id": "w19"}], "id": "w14"}, {"tokens": [{"text": "Judecătorii", "id": "w21"}, {"text": "UE", "id": "w22"}, {"text": "au", "id": "w23"}, {"text": "decis", "id": "w24"}, {"text": "că", "id": "w25"}, {"text": "un", "id": "w26"}, {"text": "fost", "id": "w27"}, {"text": "luptător", "id": "w28"}, {"text": "de", "id": "w29"}, {"text": "gherilă", "id": "w30"}, {"text": "a", "id": "w31"}, {"text": "comis", "id": "w32"}, {"text": "crime", "id": "w33.0"}, {"text": "de", "id": "w33.1"}, {"text": "război", "id": "w33.2"}, {"text": "atunci", "id": "w34.0"}, {"text": "când", "id": "w34.1"}, {"ant": "w28", "agreement": "high", "dep_head": "w35", "id": "w34.5"}, {"text": "a", "id": "w35"}, {"text": "tras", "id": "w36"}, {"text": "asupra", "id": "w37"}, {"text": "unei", "id": "w38"}, {"text": "familii", "id": "w39"}, {"text": "care", "id": "w40"}, {"text": "fugea", "id": "w41"}, {"text": "printr-", "id": "w42"}, {"text": "un", "id": "w43"}, {"text": "punct", "id": "w44"}, {"text": "de", "id": "w45"}, {"text": "control", "id": "w46"}, {"text": "al", "id": "w47"}, {"text": "KLA", "id": "w48"}, {"text": ".", "id": "w49"}], "id": "w20"}, {"tokens": [{"text": "(", "id": "w51"}, {"text": "Reuters", "id": "w52"}, {"text": ",", "id": "w53"}, {"text": "AP", "id": "w54"}, {"text": ",", "id": "w55"}, {"text": "AFP", "id": "w56"}, {"text": ",", "id": "w57"}, {"text": "DPA", "id": "w58"}, {"text": ",", "id": "w59"}, {"text": "Deutsche", "id": "w60"}, {"text": "Welle", "id": "w61"}, {"text": ",", "id": "w62"}, {"text": "AKI", "id": "w63"}, {"text": ",", "id": "w64"}, {"text": "B92", "id": "w65"}, {"text": "-", "id": "w66"}, {"text": "04", "id": "w67"}, {"text": "/", "id": "w68"}, {"text": "02", "id": "w69"}, {"text": "/", "id": "w70"}, {"text": "09", "id": "w71"}, {"text": ";", "id": "w72"}, {"text": "BBC", "id": "w73"}, {"text": "-", "id": "w74"}, {"text": "03", "id": "w75"}, {"text": "/", "id": "w76"}, {"text": "02", "id": "w77"}, {"text": "/", "id": "w78"}, {"text": "09", "id": "w79"}, {"text": ")", "id": "w80"}], "id": "w50"}, {"tokens": [{"text": "Un", "id": "w82"}, {"text": "bărbat", "id": "w83"}, {"text": "a", "id": "w84"}, {"text": "primit", "id": "w85"}, {"text": "o", "id": "w86"}, {"text": "sentință", "id": "w87"}, {"text": "de", "id": "w88"}, {"text": "17", "id": "w89"}, {"text": "ani", "id": "w90"}, {"text": "de", "id": "w91"}, {"text": "închisoare", "id": "w92"}, {"text": "în", "id": "w93"}, {"text": "primul", "id": "w94"}, {"text": "proces", "id": "w95"}, {"text": "pentru", "id": "w96"}, {"text": "crime", "id": "w97.0"}, {"text": "de", "id": "w97.1"}, {"text": "război", "id": "w97.2"}, {"text": "derulat", "id": "w98"}, {"text": "sub", "id": "w99"}, {"text": "auspiciile", "id": "w100"}, {"text": "EULEX", "id": "w101"}, {"text": ".", "id": "w102"}], "id": "w81"}, {"tokens": [{"text": "[", "id": "w104"}, {"text": "EULEX", "id": "w105"}, {"text": "]", "id": "w106"}], "id": "w103"}, {"tokens": [{"text": "Un", "id": "w108"}, {"text": "fost", "id": "w109"}, {"text": "membru", "id": "w110"}, {"text": "al", "id": "w111"}, {"text": "Armatei", "id": "w112"}, {"text": "de", "id": "w113"}, {"text": "Eliberare", "id": "w114"}, {"text": "a", "id": "w115"}, {"text": "Kosovo", "id": "w116"}, {"text": "(", "id": "w117"}, {"text": "KLA", "id": "w118"}, {"text": ")", "id": "w119"}, {"text": "a", "id": "w120"}, {"text": "primit", "id": "w121"}, {"text": "o", "id": "w122"}, {"text": "sentință", "id": "w123"}, {"text": "de", "id": "w124"}, {"text": "17", "id": "w125"}, {"text": "ani", "id": "w126"}, {"text": "de", "id": "w127"}, {"text": "închisoare", "id": "w128"}, {"text": "pentru", "id": "w129"}, {"text": "un", "id": "w130"}, {"text": "incident", "id": "w131"}, {"text": "produs", "id": "w132"}, {"text": "în", "id": "w133"}, {"text": "1998", "id": "w134"}, {"text": ",", "id": "w135"}, {"text": "a", "id": "w136"}, {"text": "declarat", "id": "w137"}, {"text": "misiunea", "id": "w138"}, {"text": "judiciară", "id": "w139"}, {"text": "a", "id": "w140"}, {"text": "UE", "id": "w141"}, {"text": ",", "id": "w142"}, {"text": "EULEX", "id": "w143"}, {"text": ",", "id": "w144"}, {"text": "miercuri", "id": "w145"}, {"text": "(", "id": "w146"}, {"text": "4", "id": "w147"}, {"text": "martie", "id": "w148"}, {"text": ")", "id": "w149"}, {"text": ".", "id": "w150"}], "id": "w107"}, {"tokens": [{"text": "Anunțul", "id": "w152"}, {"text": "a", "id": "w153"}, {"text": "fost", "id": "w154"}, {"text": "făcut", "id": "w155"}, {"text": "după", "id": "w156"}, {"text": "finalizarea", "id": "w157"}, {"text": "primului", "id": "w158"}, {"text": "proces", "id": "w159"}, {"text": "de", "id": "w160"}, {"text": "crime", "id": "w161.0"}, {"text": "de", "id": "w161.1"}, {"text": "război", "id": "w161.2"}, {"text": "derulat", "id": "w162"}, {"text": "sub", "id": "w163"}, {"text": "auspiciile", "id": "w164"}, {"text": "misiunii", "id": "w165"}, {"text": ".", "id": "w166"}], "id": "w151"}, {"tokens": [{"text": "O", "id": "w168"}, {"text": "comisie", "id": "w169"}, {"text": "formată", "id": "w170"}, {"text": "din", "id": "w171"}, {"text": "doi", "id": "w172"}, {"text": "judecători", "id": "w173"}, {"text": "internaționali", "id": "w174"}, {"text": "și", "id": "w175"}, {"text": "unul", "id": "w176"}, {"text": "din", "id": "w177"}, {"text": "Kosovo", "id": "w178"}, {"text": "l-", "id": "w179"}, {"text": "a", "id": "w180"}, {"text": "găsit", "id": "w181"}, {"text": "pe", "id": "w182"}, {"text": "Gani", "id": "w183"}, {"text": "Gashi", "id": "w184"}, {"text": ",", "id": "w185"}, {"text": "în", "id": "w186"}, {"text": "vârstă", "id": "w187"}, {"text": "de", "id": "w188"}, {"text": "59", "id": "w189"}, {"text": "de", "id": "w190"}, {"text": "ani", "id": "w191"}, {"text": ",", "id": "w192"}, {"text": "\"", "id": "w193"}, {"text": "vinovat", "id": "w194"}, {"text": "de", "id": "w195"}, {"text": "crimă", "id": "w196"}, {"text": ",", "id": "w197"}, {"text": "tentativă", "id": "w198"}, {"text": "de", "id": "w199"}, {"text": "crimă", "id": "w200"}, {"text": "și", "id": "w201"}, {"text": "vătămare", "id": "w202"}, {"text": "corporală", "id": "w203"}, {"text": "gravă", "id": "w204"}, {"text": "\"", "id": "w205"}, {"text": ",", "id": "w206"}, {"text": "a", "id": "w207"}, {"text": "afirmat", "id": "w208"}, {"text": "EULEX", "id": "w209"}, {"text": "într-", "id": "w210"}, {"text": "o", "id": "w211"}, {"text": "declarație", "id": "w212"}, {"text": ".", "id": "w213"}], "id": "w167"}, {"tokens": [{"text": "În", "id": "w215"}, {"text": "12", "id": "w216"}, {"text": "iulie", "id": "w217"}, {"text": "1998", "id": "w218"}, {"text": ",", "id": "w219"}, {"text": "Gashi", "id": "w220"}, {"text": "opera", "id": "w221"}, {"text": "un", "id": "w222"}, {"text": "punct", "id": "w223"}, {"text": "de", "id": "w224"}, {"text": "control", "id": "w225"}, {"text": "din", "id": "w226"}, {"text": "centrul", "id": "w227"}, {"text": "Kosovo", "id": "w228"}, {"text": "înființat", "id": "w229"}, {"text": "de", "id": "w230"}, {"text": "Armata", "id": "w231"}, {"text": "de", "id": "w232"}, {"text": "Eliberare", "id": "w233"}, {"text": "a", "id": "w234"}, {"text": "Kosovo", "id": "w235"}, {"text": "--", "id": "w236"}, {"text": "pe", "id": "w237.0"}, {"text": "atunci", "id": "w237.1"}, {"text": "un", "id": "w238"}, {"text": "grup", "id": "w239"}, {"text": "de", "id": "w240"}, {"text": "gherilă", "id": "w241"}, {"text": "care", "id": "w242"}, {"text": "purta", "id": "w243"}, {"text": "o", "id": "w244"}, {"text": "campanie", "id": "w245"}, {"text": "armată", "id": "w246"}, {"text": "împotriva", "id": "w247"}, {"text": "autorităților", "id": "w248"}, {"text": "sârbe", "id": "w249"}, {"text": ".", "id": "w250"}], "id": "w214"}, {"tokens": [{"text": "O", "id": "w252"}, {"text": "familie", "id": "w253"}, {"text": "albaneză", "id": "w254"}, {"text": "kosovară", "id": "w255"}, {"text": "care", "id": "w256"}, {"text": "încerca", "id": "w257"}, {"ant": "w253", "agreement": "high", "dep_head": "w259", "id": "w257.5"}, {"text": "să", "id": "w258"}, {"text": "fugă", "id": "w259"}, {"text": "de", "id": "w260"}, {"text": "luptele", "id": "w261"}, {"text": "dintre", "id": "w262"}, {"text": "militanți", "id": "w263"}, {"text": "și", "id": "w264"}, {"text": "forțele", "id": "w265"}, {"text": "sârbe", "id": "w266"}, {"text": "a", "id": "w267"}, {"text": "trecut", "id": "w268"}, {"text": "prin", "id": "w269"}, {"text": "punctul", "id": "w270"}, {"text": "de", "id": "w271"}, {"text": "control", "id": "w272"}, {"text": ",", "id": "w273"}, {"text": "dar", "id": "w274"}, {"ant": "w253", "agreement": "high", "dep_head": "w277", "id": "w274.5"}, {"text": "nu", "id": "w275"}, {"text": "s-", "id": "w276"}, {"text": "a", "id": "w277"}, {"text": "oprit", "id": "w278"}, {"text": ".", "id": "w279"}], "id": "w251"}, {"tokens": [{"text": "Gashi", "id": "w281"}, {"text": "a", "id": "w282"}, {"text": "deschis", "id": "w283"}, {"text": "atunci", "id": "w284"}, {"text": "focul", "id": "w285"}, {"text": ".", "id": "w286"}], "id": "w280"}, {"tokens": [{"text": "Un", "id": "w288"}, {"text": "membru", "id": "w289"}, {"text": "al", "id": "w290"}, {"text": "familiei", "id": "w291"}, {"text": "Obrija", "id": "w292"}, {"text": "|", "id": "w293"}, {"text": "--", "id": "w294"}, {"text": "a", "id": "w295"}, {"text": "murit", "id": "w296"}, {"text": "în", "id": "w297"}, {"text": "incident", "id": "w298"}, {"text": ".", "id": "w299"}], "id": "w287"}, {"tokens": [{"text": "Soția", "id": "w301"}, {"text": "sa", "id": "w302"}, {"text": ",", "id": "w303"}, {"text": "fiul", "id": "w304"}, {"text": "și", "id": "w305"}, {"text": "un", "id": "w306"}, {"text": "nepot", "id": "w307"}, {"text": "au", "id": "w308"}, {"text": "fost", "id": "w309"}, {"text": "grav", "id": "w310"}, {"text": "răniți", "id": "w311"}, {"text": ".", "id": "w312"}], "id": "w300"}, {"tokens": [{"text": "\"", "id": "w314"}, {"text": "Prin", "id": "w315"}, {"text": "acest", "id": "w316"}, {"text": "act", "id": "w317"}, {"text": ",", "id": "w318"}, {"text": "Gani", "id": "w319"}, {"text": "Gashi", "id": "w320"}, {"text": "a", "id": "w321"}, {"text": "comis", "id": "w322"}, {"text": "o", "id": "w323"}, {"text": "crimă", "id": "w324.0"}, {"text": "de", "id": "w324.1"}, {"text": "război", "id": "w324.2"}, {"text": "împotriva", "id": "w325"}, {"text": "populației", "id": "w326"}, {"text": "civile", "id": "w327"}, {"text": ",", "id": "w328"}, {"text": "un", "id": "w329"}, {"text": "delict", "id": "w330"}, {"text": "penal", "id": "w331"}, {"text": "ce", "id": "w332"}, {"text": "este", "id": "w333"}, {"text": "pedepsit", "id": "w334"}, {"text": "conform", "id": "w335"}, {"text": "legii", "id": "w336"}, {"text": "kosovare", "id": "w337"}, {"text": "și", "id": "w338"}, {"text": "internaționale", "id": "w339"}, {"text": "\"", "id": "w340"}, {"text": ",", "id": "w341"}, {"text": "au", "id": "w342"}, {"text": "declarat", "id": "w343"}, {"text": "judecătorii", "id": "w344"}, {"text": "în", "id": "w345"}, {"text": "sentința", "id": "w346"}, {"text": "de", "id": "w347"}, {"text": "marți", "id": "w348"}, {"text": ".", "id": "w349"}], "id": "w313"}, {"tokens": [{"text": "KLA", "id": "w351"}, {"text": "a", "id": "w352"}, {"text": "început", "id": "w353"}, {"text": "să", "id": "w354"}, {"text": "atace", "id": "w355"}, {"text": "secțiile", "id": "w356"}, {"text": "de", "id": "w357"}, {"text": "poliție", "id": "w358"}, {"text": ",", "id": "w359"}, {"text": "oficiile", "id": "w360"}, {"text": "guvernamentale", "id": "w361"}, {"text": "și", "id": "w362"}, {"text": "alte", "id": "w363"}, {"text": "instituții", "id": "w364"}, {"text": "conduse", "id": "w365"}, {"text": "de", "id": "w366"}, {"text": "sârbi", "id": "w367"}, {"text": "în", "id": "w368"}, {"text": "1996", "id": "w369"}, {"text": ".", "id": "w370"}], "id": "w350"}, {"tokens": [{"text": "Aceasta", "id": "w372"}, {"text": "s-", "id": "w373"}, {"text": "a", "id": "w374"}, {"text": "aflat", "id": "w375"}, {"text": "pentru", "id": "w376.0"}, {"text": "o", "id": "w376.1"}, {"text": "vreme", "id": "w376.2"}, {"text": "pe", "id": "w377"}, {"text": "lista", "id": "w378"}, {"text": "de", "id": "w379"}, {"text": "grupuri", "id": "w380"}, {"text": "teroriste", "id": "w381"}, {"text": "a", "id": "w382"}, {"text": "Departamentului", "id": "w383"}, {"text": "de", "id": "w384"}, {"text": "Stat", "id": "w385"}, {"text": "al", "id": "w386"}, {"text": "SUA", "id": "w387"}, {"text": ".", "id": "w388"}], "id": "w371"}, {"tokens": [{"text": "Se", "id": "w390"}, {"text": "credea", "id": "w391"}, {"text": "că", "id": "w392"}, {"text": "gruparea", "id": "w393"}, {"text": "a", "id": "w394"}, {"text": "obținut", "id": "w395"}, {"text": "o", "id": "w396"}, {"text": "mare", "id": "w397"}, {"text": "parte", "id": "w398"}, {"text": "din", "id": "w399"}, {"text": "fondurile", "id": "w400"}, {"text": "sale", "id": "w401"}, {"text": "din", "id": "w402"}, {"text": "traficul", "id": "w403"}, {"text": "de", "id": "w404"}, {"text": "narcotice", "id": "w405"}, {"text": "și", "id": "w406"}, {"text": "că", "id": "w407"}, {"ant": "w393", "agreement": "high", "dep_head": "w408", "id": "w407.5"}, {"text": "a", "id": "w408"}, {"text": "întreținut", "id": "w409"}, {"text": "legături", "id": "w410"}, {"text": "cu", "id": "w411"}, {"text": "rețeaua", "id": "w412"}, {"text": "teroristă", "id": "w413"}, {"text": "a", "id": "w414"}, {"text": "lui", "id": "w415"}, {"text": "Osama", "id": "w416"}, {"text": "bin", "id": "w417"}, {"text": "Laden", "id": "w418"}, {"text": ",", "id": "w419"}, {"text": "al-Qaeda", "id": "w420"}, {"text": ".", "id": "w421"}], "id": "w389"}, {"tokens": [{"text": "Potrivit", "id": "w423"}, {"text": "ONG", "id": "w424"}, {"text": "-ului", "id": "w425"}, {"text": "Human", "id": "w426"}, {"text": "Rights", "id": "w427"}, {"text": "Watch", "id": "w428"}, {"text": ",", "id": "w429"}, {"text": "membrii", "id": "w430"}, {"text": "KLA", "id": "w431"}, {"text": "au", "id": "w432"}, {"text": "comis", "id": "w433"}, {"text": "\"", "id": "w434"}, {"text": "abuzuri", "id": "w435"}, {"text": "grave", "id": "w436"}, {"text": "\"", "id": "w437"}, {"text": ",", "id": "w438"}, {"text": "răpind", "id": "w439"}, {"text": "și", "id": "w440"}, {"text": "omorând", "id": "w441"}, {"text": "civili", "id": "w442"}, {"text": "sârbi", "id": "w443"}, {"text": "și", "id": "w444"}, {"text": "albanezi", "id": "w445"}, {"text": "kosovari", "id": "w446"}, {"text": "considerați", "id": "w447"}, {"text": "colaboratori", "id": "w448"}, {"text": "sau", "id": "w449"}, {"text": "refractari", "id": "w450"}, {"text": "față", "id": "w451.0"}, {"text": "de", "id": "w451.1"}, {"text": "scopurile", "id": "w452"}, {"text": "grupului", "id": "w453"}, {"text": "de", "id": "w454"}, {"text": "gherilă", "id": "w455"}, {"text": ".", "id": "w456"}], "id": "w422"}, {"tokens": [{"text": "Într-", "id": "w458"}, {"text": "un", "id": "w459"}, {"text": "caz", "id": "w460"}, {"text": "extrem", "id": "w461.0"}, {"text": "de", "id": "w461.1"}, {"text": "mediatizat", "id": "w462"}, {"text": ",", "id": "w463"}, {"text": "un", "id": "w464"}, {"text": "grup", "id": "w465"}, {"text": "de", "id": "w466"}, {"text": "extremiști", "id": "w467"}, {"text": "suspectați", "id": "w468"}, {"text": "că", "id": "w469"}, {"ant": "w467", "agreement": "high", "dep_head": "w470", "id": "w469.5"}, {"text": "ar", "id": "w470"}, {"text": "fi", "id": "w471"}, {"text": "avut", "id": "w472"}, {"text": "legături", "id": "w473"}, {"text": "cu", "id": "w474"}, {"text": "KLA", "id": "w475"}, {"text": "au", "id": "w476"}, {"text": "bombardat", "id": "w477"}, {"text": "un", "id": "w478"}, {"text": "autobuz", "id": "w479"}, {"text": "care", "id": "w480"}, {"text": "transporta", "id": "w481"}, {"text": "sârbi", "id": "w482"}, {"text": "aflați", "id": "w483"}, {"text": "în", "id": "w484"}, {"text": "drum", "id": "w485"}, {"text": "spre", "id": "w486"}, {"text": "mănăstirea", "id": "w487"}, {"text": "Gracanica", "id": "w488"}, {"text": ".", "id": "w489"}], "id": "w457"}, {"tokens": [{"text": "Doisprezece", "id": "w491"}, {"text": "sârbi", "id": "w492"}, {"text": "au", "id": "w493"}, {"text": "fost", "id": "w494"}, {"text": "uciși", "id": "w495"}, {"text": "și", "id": "w496"}, {"text": "mulți", "id": "w497"}, {"text": "alții", "id": "w498"}, {"text": "au", "id": "w499"}, {"text": "fost", "id": "w500"}, {"text": "răniți", "id": "w501"}, {"text": ".", "id": "w502"}], "id": "w490"}, {"tokens": [{"text": "Misiunea", "id": "w504"}, {"text": "EULEX", "id": "w505"}, {"text": "este", "id": "w506"}, {"text": "condusă", "id": "w507"}, {"text": "de", "id": "w508"}, {"text": "Yves", "id": "w509"}, {"text": "de", "id": "w510"}, {"text": "Kermabon", "id": "w511"}, {"text": "din", "id": "w512"}, {"text": "Franța", "id": "w513"}, {"text": ".", "id": "w514"}], "id": "w503"}, {"tokens": [{"text": "Aceasta", "id": "w516"}, {"text": "și-", "id": "w517"}, {"text": "a", "id": "w518"}, {"text": "început", "id": "w519"}, {"text": "în", "id": "w520"}, {"text": "mod", "id": "w521"}, {"text": "oficial", "id": "w522"}, {"text": "operațiunile", "id": "w523"}, {"text": "în", "id": "w524"}, {"text": "Kosovo", "id": "w525"}, {"text": "la", "id": "w526"}, {"text": "începutul", "id": "w527"}, {"text": "lunii", "id": "w528"}, {"text": "decembrie", "id": "w529"}, {"text": ",", "id": "w530"}, {"text": "înlocuind", "id": "w531"}, {"text": "UNMIK", "id": "w532"}, {"text": "după", "id": "w533"}, {"text": "mai", "id": "w534"}, {"text": "mult", "id": "w535"}, {"text": "de", "id": "w536"}, {"text": "nouă", "id": "w537"}, {"text": "ani", "id": "w538"}, {"text": "de", "id": "w539.0"}, {"text": "la", "id": "w539.1"}, {"text": "lansarea", "id": "w540"}, {"text": "sa", "id": "w541"}, {"text": "în", "id": "w542"}, {"text": "iunie", "id": "w543"}, {"text": "1999", "id": "w544"}, {"text": ".", "id": "w545"}], "id": "w515"}, {"tokens": [{"text": "Personalul", "id": "w547"}, {"text": "EULEX", "id": "w548"}, {"text": "numără", "id": "w549"}, {"text": "în", "id": "w550.0"}, {"text": "prezent", "id": "w550.1"}, {"text": "aproximativ", "id": "w551"}, {"text": "2500", "id": "w552"}, {"text": "de", "id": "w553"}, {"text": "membri", "id": "w554"}, {"text": ",", "id": "w555"}, {"text": "1690", "id": "w556"}, {"text": "dintre", "id": "w557"}, {"text": "aceștia", "id": "w558"}, {"text": "fiind", "id": "w559"}, {"text": "străini", "id": "w560"}, {"text": "și", "id": "w561"}, {"text": "aproape", "id": "w562"}, {"text": "800", "id": "w563"}, {"text": "kosovari", "id": "w564"}, {"text": ".", "id": "w565"}], "id": "w546"}, {"tokens": [{"text": "Procesul", "id": "w567"}, {"text": "lui", "id": "w568"}, {"text": "Gashi", "id": "w569"}, {"text": "este", "id": "w570"}, {"text": "primul", "id": "w571"}, {"text": "proces", "id": "w572"}, {"text": "în", "id": "w573"}, {"text": "care", "id": "w574"}, {"text": "membrii", "id": "w575"}, {"text": "misiunii", "id": "w576"}, {"text": "au", "id": "w577"}, {"text": "lucrat", "id": "w578"}, {"text": "în", "id": "w579"}, {"text": "strânsă", "id": "w580"}, {"text": "cooperare", "id": "w581"}, {"text": "cu", "id": "w582"}, {"text": "tribunalele", "id": "w583"}, {"text": "kosovare", "id": "w584"}, {"text": ".", "id": "w585"}], "id": "w566"}, {"tokens": [{"text": "\"", "id": "w587"}, {"text": "Acest", "id": "w588"}, {"text": "proces", "id": "w589"}, {"text": "arată", "id": "w590"}, {"text": "că", "id": "w591"}, {"text": "EULEX", "id": "w592"}, {"text": "este", "id": "w593"}, {"text": "serioasă", "id": "w594"}, {"text": "în", "id": "w595.0"}, {"text": "legătură", "id": "w595.1"}, {"text": "cu", "id": "w595.2"}, {"text": "investigarea", "id": "w596"}, {"text": "și", "id": "w597"}, {"text": "judecarea", "id": "w598"}, {"text": "cazurilor", "id": "w599"}, {"text": "de", "id": "w600"}, {"text": "crime", "id": "w601.0"}, {"text": "de", "id": "w601.1"}, {"text": "război", "id": "w601.2"}, {"text": "ori", "id": "w602.0"}, {"text": "de", "id": "w602.1"}, {"text": "câte", "id": "w602.2"}, {"text": "ori", "id": "w602.3"}, {"text": "acestea", "id": "w603"}, {"text": "au", "id": "w604"}, {"text": "avut", "id": "w605"}, {"text": "loc", "id": "w606"}, {"text": ",", "id": "w607"}, {"text": "câtă", "id": "w608"}, {"text": "vreme", "id": "w609"}, {"ant": "elliptic", "agreement": "high", "dep_head": "w610", "id": "w609.5"}, {"text": "avem", "id": "w610"}, {"text": "suficiente", "id": "w611"}, {"text": "dovezi", "id": "w612"}, {"text": "pentru", "id": "w613"}, {"text": "a", "id": "w614"}, {"text": "judeca", "id": "w615"}, {"text": "cu", "id": "w616"}, {"text": "succes", "id": "w617"}, {"text": "cazul", "id": "w618"}, {"text": "\"", "id": "w619"}, {"text": ",", "id": "w620"}, {"text": "a", "id": "w621"}, {"text": "declarat", "id": "w622"}, {"text": "procurorul", "id": "w623"}, {"text": "-șef", "id": "w624"}, {"text": "al", "id": "w625"}, {"text": "EULEX", "id": "w626"}, {"text": "Theo", "id": "w627"}, {"text": "Jacobs", "id": "w628"}, {"text": "miercuri", "id": "w629"}, {"text": ",", "id": "w630"}, {"text": "salutând", "id": "w631"}, {"text": "verdictul", "id": "w632"}, {"text": ".", "id": "w633"}], "id": "w586"}, {"tokens": [{"text": "\"", "id": "w635"}, {"ant": "elliptic", "agreement": "high", "dep_head": "w636", "id": "w635.5"}, {"text": "Vom", "id": "w636"}, {"text": "face", "id": "w637"}, {"text": "aceasta", "id": "w638"}, {"text": "indiferent", "id": "w639"}, {"text": "de", "id": "w640"}, {"text": "etnia", "id": "w641"}, {"text": "celor", "id": "w642"}, {"text": "implicați", "id": "w643"}, {"text": "în", "id": "w644"}, {"text": "crimă", "id": "w645"}, {"text": "\"", "id": "w646"}, {"text": ".", "id": "w647"}], "id": "w634"}, {"tokens": [{"text": "Miercuri", "id": "w649"}, {"text": "a", "id": "w650"}, {"text": "reprezentat", "id": "w651"}, {"text": "și", "id": "w652"}, {"text": "lansarea", "id": "w653"}, {"text": "unui", "id": "w654"}, {"text": "proces", "id": "w655"}, {"text": "penal", "id": "w656"}, {"text": "condus", "id": "w657"}, {"text": "de", "id": "w658"}, {"text": "EULEX", "id": "w659"}, {"text": "în", "id": "w660"}, {"text": "Mitrovica", "id": "w661"}, {"text": ",", "id": "w662"}, {"text": "orașul", "id": "w663"}, {"text": "kosovar", "id": "w664"}, {"text": "divizat", "id": "w665"}, {"text": "etnic", "id": "w666"}, {"text": ".", "id": "w667"}], "id": "w648"}, {"tokens": [{"text": "Inițial", "id": "w669"}, {"text": ",", "id": "w670"}, {"text": "curtea", "id": "w671"}, {"text": "intenționa", "id": "w672"}, {"text": "să", "id": "w673"}, {"text": "înceapă", "id": "w674"}, {"text": "procesul", "id": "w675"}, {"text": "luni", "id": "w676"}, {"text": ",", "id": "w677"}, {"text": "însă", "id": "w678"}, {"text": "aproximativ", "id": "w679"}, {"text": "100", "id": "w680"}, {"text": "de", "id": "w681"}, {"text": "protestatari", "id": "w682"}, {"text": "sârbi", "id": "w683"}, {"text": "kosovari", "id": "w684"}, {"text": "i-", "id": "w685"}, {"text": "au", "id": "w686"}, {"text": "împiedicat", "id": "w687"}, {"text": "pe", "id": "w688"}, {"text": "judecătorii", "id": "w689"}, {"text": "UE", "id": "w690"}, {"ant": "w689", "agreement": "high", "dep_head": "w692", "id": "w690.5"}, {"text": "să", "id": "w691"}, {"text": "intre", "id": "w692"}, {"text": "în", "id": "w693"}, {"text": "sala", "id": "w694"}, {"text": "de", "id": "w695"}, {"text": "judecată", "id": "w696"}, {"text": ".", "id": "w697"}], "id": "w668"}, {"tokens": [{"text": "Din", "id": "w699.0"}, {"text": "cauza", "id": "w699.1"}, {"text": "temerilor", "id": "w700"}, {"text": "legate", "id": "w701"}, {"text": "de", "id": "w702"}, {"text": "securitate", "id": "w703"}, {"text": ",", "id": "w704"}, {"text": "prima", "id": "w705"}, {"text": "audiere", "id": "w706"}, {"text": "a", "id": "w707"}, {"text": "fost", "id": "w708"}, {"text": "amânată", "id": "w709"}, {"text": "până", "id": "w710"}, {"text": "miercuri", "id": "w711"}, {"text": ".", "id": "w712"}], "id": "w698"}, {"tokens": [{"text": "Potrivit", "id": "w714"}, {"text": "surselor", "id": "w715"}, {"text": ",", "id": "w716"}, {"text": "procesul", "id": "w717"}, {"text": "se", "id": "w718"}, {"text": "referă", "id": "w719"}, {"text": "la", "id": "w720"}, {"text": "un", "id": "w721"}, {"text": "jaf", "id": "w722"}, {"text": "grav", "id": "w723"}, {"text": "din", "id": "w724"}, {"text": "2007", "id": "w725"}, {"text": "în", "id": "w726"}, {"text": "care", "id": "w727"}, {"text": "sunt", "id": "w728"}, {"text": "implicați", "id": "w729"}, {"text": "doi", "id": "w730"}, {"text": "sârbi", "id": "w731"}, {"text": "kosovari", "id": "w732"}, {"text": ".", "id": "w733"}], "id": "w713"}, {"tokens": [{"text": "\"", "id": "w735"}, {"text": "Procesul", "id": "w736"}, {"text": "a", "id": "w737"}, {"text": "început", "id": "w738"}, {"text": "astăzi", "id": "w739"}, {"text": "fără", "id": "w740"}, {"text": "nici", "id": "w741.0"}, {"text": "o", "id": "w741.1"}, {"text": "problemă", "id": "w742"}, {"text": "\"", "id": "w743"}, {"text": ",", "id": "w744"}, {"text": "a", "id": "w745"}, {"text": "declarat", "id": "w746"}, {"text": "purtătoarea", "id": "w747"}, {"text": "de", "id": "w748"}, {"text": "cuvânt", "id": "w749"}, {"text": "a", "id": "w750"}, {"text": "EULEX", "id": "w751"}, {"text": ",", "id": "w752"}, {"text": "Kristina", "id": "w753"}, {"text": "Herodes", "id": "w754"}, {"text": ",", "id": "w755"}, {"text": "agenției", "id": "w756"}, {"text": "AFP", "id": "w757"}, {"text": ",", "id": "w758"}, {"text": "după", "id": "w759"}, {"text": "sesiunea", "id": "w760"}, {"text": "de", "id": "w761"}, {"text": "miercuri", "id": "w762"}, {"text": ".", "id": "w763"}], "id": "w734"}, {"tokens": [{"text": "Kosovo", "id": "w765"}, {"text": "și-", "id": "w766"}, {"text": "a", "id": "w767"}, {"text": "declarat", "id": "w768"}, {"text": "independența", "id": "w769"}, {"text": "față", "id": "w770.0"}, {"text": "de", "id": "w770.1"}, {"text": "Serbia", "id": "w771"}, {"text": "în", "id": "w772"}, {"text": "17", "id": "w773"}, {"text": "februarie", "id": "w774"}, {"text": "2008", "id": "w775"}, {"text": ",", "id": "w776"}, {"text": "în", "id": "w777.0"}, {"text": "ciuda", "id": "w777.1"}, {"text": "opoziției", "id": "w778"}, {"text": "înverșunate", "id": "w779"}, {"text": "a", "id": "w780"}, {"text": "Belgradului", "id": "w781"}, {"text": "și", "id": "w782"}, {"text": "a", "id": "w783"}, {"text": "sârbilor", "id": "w784"}, {"text": "kosovari", "id": "w785"}], "id": "w764"}]}